alchemy_h8/__init__.py
alchemy_h8/circuit_breaker.py
alchemy_h8/config.py
alchemy_h8/connection.py
alchemy_h8/rate_limiter.py
alchemy_h8-0.1.3.dist-info/METADATA
alchemy_h8-0.1.3.dist-info/WHEEL
alchemy_h8-0.1.3.dist-info/RECORD
