Metadata-Version: 2.4
Name: alchemy-h8
Version: 0.1.3
Summary: Advanced SQLAlchemy extension with connection pooling, rate limiting, and security features
Project-URL: Documentation, https://github.com/Harut8/alchemy_h8#readme
Project-URL: Issues, https://github.com/Harut8/alchemy_h8/issues
Project-URL: Source, https://github.com/Harut8/alchemy_h8
Author-email: Harut <har.avetisyan2002@gmail.com>
License: MIT
Keywords: async,connection-pooling,database,postgresql,rate-limiting,sqlalchemy
Classifier: Development Status :: 4 - Beta
Classifier: Intended Audience :: Developers
Classifier: License :: OSI Approved :: MIT License
Classifier: Programming Language :: Python :: 3
Classifier: Programming Language :: Python :: 3.11
Classifier: Programming Language :: Python :: 3.12
Classifier: Topic :: Database
Classifier: Topic :: Software Development :: Libraries :: Python Modules
Classifier: Typing :: Typed
Requires-Python: >=3.11
Requires-Dist: asyncpg>=0.30.0
Requires-Dist: greenlet>=3.2.3
Requires-Dist: pydantic>=2.11.7
Requires-Dist: sqlalchemy>=2.0.41
Requires-Dist: structlog>=25.4.0
Requires-Dist: tenacity>=9.1.2
Provides-Extra: dev
Requires-Dist: black>=24.4.0; extra == 'dev'
Requires-Dist: flake8>=7.0.0; extra == 'dev'
Requires-Dist: isort>=5.13.2; extra == 'dev'
Requires-Dist: mypy>=1.8.0; extra == 'dev'
Requires-Dist: pytest-asyncio>=0.23.5; extra == 'dev'
Requires-Dist: pytest-cov>=5.0.0; extra == 'dev'
Requires-Dist: pytest>=8.4.1; extra == 'dev'
Requires-Dist: sphinx-rtd-theme>=2.0.0; extra == 'dev'
Requires-Dist: sphinx>=7.3.7; extra == 'dev'
Requires-Dist: sqlalchemy-stubs>=0.4; extra == 'dev'
Provides-Extra: test
Requires-Dist: pytest-asyncio>=0.23.5; extra == 'test'
Requires-Dist: pytest-cov>=5.0.0; extra == 'test'
Requires-Dist: pytest>=8.4.1; extra == 'test'
